llm_interface/__init__.py
llm_interface/anthropic.py
llm_interface/errors.py
llm_interface/gemini.py
llm_interface/llm_config.py
llm_interface/llm_interface.py
llm_interface/llm_tool.py
llm_interface/ollama.py
llm_interface/openai.py
llm_interface/openrouter.py
llm_interface/pydantic_output_parser.py
llm_interface/remote_ollama.py
llm_interface/ssh.py
llm_interface/testing/__init__.py
llm_interface/testing/helpers.py
llm_interface/testing/mock_llm.py
llm_interface/token_usage.py
llm_interface/utils.py
llm_interface-0.1.13.dist-info/LICENSE
llm_interface-0.1.13.dist-info/METADATA
llm_interface-0.1.13.dist-info/WHEEL
llm_interface-0.1.13.dist-info/RECORD
