Metadata-Version: 2.3
Name: llm-interface
Version: 0.1.13
Summary: A flexible interface for working with various LLM providers
License: Apache-2.0
Author: Niels Provos
Author-email: provos@gmail.com
Requires-Python: >=3.10,<4.0
Classifier: License :: OSI Approved :: Apache Software License
Classifier: Programming Language :: Python :: 3
Classifier: Programming Language :: Python :: 3.10
Classifier: Programming Language :: Python :: 3.11
Classifier: Programming Language :: Python :: 3.12
Classifier: Programming Language :: Python :: 3.13
Requires-Dist: anthropic (>=0.34.2)
Requires-Dist: diskcache (>=5.6.3)
Requires-Dist: google-genai (>=1.2.0,<2.0.0)
Requires-Dist: ollama (>=0.4.7,<0.5.0)
Requires-Dist: openai (>=1.42.0)
Requires-Dist: paramiko (>=3.4.1)
Requires-Dist: pydantic (>=2.8.2)
Requires-Dist: python-dotenv (>=1.0.1)
Requires-Dist: requests (>=2.32,<3.0)
